hostingde/__init__.py
hostingde/api/__init__.py
hostingde/api/client.py
hostingde/api/dns.py
hostingde/api/errors.py
hostingde/helpers/__init__.py
hostingde/helpers/dns.py
hostingde/helpers/filters.py
hostingde/plugins/__init__.py
hostingde/plugins/certbot/__init__.py
hostingde/plugins/certbot/dns_hostingde.py
no_hostingde_api-0.3.1.dist-info/LICENSE
no_hostingde_api-0.3.1.dist-info/METADATA
no_hostingde_api-0.3.1.dist-info/WHEEL
no_hostingde_api-0.3.1.dist-info/entry_points.txt
no_hostingde_api-0.3.1.dist-info/top_level.txt
no_hostingde_api-0.3.1.dist-info/RECORD
