Metadata-Version: 2.1
Name: no-hostingde-api
Version: 0.3.1
Summary: Unofficial Client for Hosting.de API
Home-page: https://github.com/DimeOne/no-hostingde-api
Author: Dominic S.
License: MIT
Keywords: hosting.de dns api client development certbot certbot-dns certbot-dns-plugin
Platform: any
Classifier: Programming Language :: Python
Classifier: Development Status :: 3 - Alpha
Classifier: Intended Audience :: Developers
Classifier: License :: OSI Approved :: MIT License
Classifier: Operating System :: OS Independent
Classifier: Programming Language :: Python :: 3.6
Classifier: Topic :: Internet :: WWW/HTTP
Classifier: Topic :: Software Development :: Libraries :: Python Modules
Requires-Python: >=2.6, !=3.0.*, !=3.1.*, !=3.2.*, <4
Requires-Dist: requests
